yabadaba/Settings.py
yabadaba/VERSION
yabadaba/__init__.py
yabadaba/check_modules.py
yabadaba/querydoc.py
yabadaba/UnitConverter/__init__.py
yabadaba/UnitConverter/_acceleration.py
yabadaba/UnitConverter/_capacitance.py
yabadaba/UnitConverter/_charge.py
yabadaba/UnitConverter/_concentration.py
yabadaba/UnitConverter/_constants.py
yabadaba/UnitConverter/_current.py
yabadaba/UnitConverter/_energy.py
yabadaba/UnitConverter/_force.py
yabadaba/UnitConverter/_frequency.py
yabadaba/UnitConverter/_length.py
yabadaba/UnitConverter/_magnetic.py
yabadaba/UnitConverter/_mass.py
yabadaba/UnitConverter/_power.py
yabadaba/UnitConverter/_pressure.py
yabadaba/UnitConverter/_resistance.py
yabadaba/UnitConverter/_temperature.py
yabadaba/UnitConverter/_time.py
yabadaba/UnitConverter/_voltage.py
yabadaba/UnitConverter/_volume.py
yabadaba/database/CDCSDatabase.py
yabadaba/database/Database.py
yabadaba/database/LocalDatabase.py
yabadaba/database/MongoDatabase.py
yabadaba/database/__init__.py
yabadaba/database/load_database.py
yabadaba/query/BoolMatchQuery.py
yabadaba/query/DateMatchQuery.py
yabadaba/query/DummyQuery.py
yabadaba/query/FloatMatchQuery.py
yabadaba/query/IntMatchQuery.py
yabadaba/query/ListContainsQuery.py
yabadaba/query/MonthMatchQuery.py
yabadaba/query/Query.py
yabadaba/query/StrContainsQuery.py
yabadaba/query/StrMatchQuery.py
yabadaba/query/__init__.py
yabadaba/record/Record.py
yabadaba/record/RecordValue.py
yabadaba/record/__init__.py
yabadaba/tools/ModuleManager.py
yabadaba/tools/__init__.py
yabadaba/tools/dict_insert.py
yabadaba/tools/is_uuid.py
yabadaba/tools/screen_input.py
yabadaba/value/BoolValue.py
yabadaba/value/DateValue.py
yabadaba/value/FloatArrayValue.py
yabadaba/value/FloatValue.py
yabadaba/value/IntArrayValue.py
yabadaba/value/IntValue.py
yabadaba/value/LongStrValue.py
yabadaba/value/MonthValue.py
yabadaba/value/StrListValue.py
yabadaba/value/StrValue.py
yabadaba/value/Value.py
yabadaba/value/__init__.py
yabadaba-0.3.2.dist-info/licenses/LICENSE.TXT
yabadaba-0.3.2.dist-info/METADATA
yabadaba-0.3.2.dist-info/WHEEL
yabadaba-0.3.2.dist-info/top_level.txt
yabadaba-0.3.2.dist-info/RECORD
