Metadata-Version: 2.4
Name: yabadaba
Version: 0.3.2
Summary: Yay, a base database! An abstraction layer allowing for common interactions with Mongo, CDCS and local directory databases and records.
Home-page: https://github.com/usnistgov/yabadaba
Author: Lucas Hale
Author-email: lucas.hale@nist.gov
Keywords: database,mongodb,CDCS
Classifier: Development Status :: 4 - Beta
Classifier: Intended Audience :: Science/Research
Classifier: Natural Language :: English
Classifier: Programming Language :: Python :: 3.8
Classifier: Programming Language :: Python :: 3.9
Classifier: Programming Language :: Python :: 3.10
Classifier: Programming Language :: Python :: 3.11
Classifier: Topic :: Scientific/Engineering :: Physics
License-File: LICENSE.TXT
Requires-Dist: lxml
Requires-Dist: DataModelDict
Requires-Dist: IPython
Requires-Dist: numpy
Requires-Dist: pandas
Requires-Dist: cdcs>=0.2.4
Requires-Dist: pymongo
Requires-Dist: tqdm
Requires-Dist: pillow
Dynamic: author
Dynamic: author-email
Dynamic: classifier
Dynamic: description
Dynamic: home-page
Dynamic: keywords
Dynamic: license-file
Dynamic: requires-dist
Dynamic: summary
